rare/__init__.py
rare/__main__.py
rare/_version.py
rare/main.py
rare/commands/__init__.py
rare/commands/reaper.py
rare/commands/webview.py
rare/commands/launcher/__init__.py
rare/commands/launcher/cloud_sync_dialog.py
rare/commands/launcher/console_dialog.py
rare/commands/launcher/lgd_helper.py
rare/components/__init__.py
rare/components/main_window.py
rare/components/tray_icon.py
rare/components/dialogs/__init__.py
rare/components/dialogs/install_dialog.py
rare/components/dialogs/launch_dialog.py
rare/components/dialogs/move_dialog.py
rare/components/dialogs/selective_dialog.py
rare/components/dialogs/uninstall_dialog.py
rare/components/dialogs/login/__init__.py
rare/components/dialogs/login/browser_login.py
rare/components/dialogs/login/import_login.py
rare/components/tabs/__init__.py
rare/components/tabs/tab_widgets.py
rare/components/tabs/account/__init__.py
rare/components/tabs/downloads/__init__.py
rare/components/tabs/downloads/download.py
rare/components/tabs/downloads/groups.py
rare/components/tabs/downloads/thread.py
rare/components/tabs/downloads/widgets.py
rare/components/tabs/library/__init__.py
rare/components/tabs/library/head_bar.py
rare/components/tabs/library/details/__init__.py
rare/components/tabs/library/details/cloud_saves.py
rare/components/tabs/library/details/details.py
rare/components/tabs/library/details/dlcs.py
rare/components/tabs/library/details/settings.py
rare/components/tabs/library/integrations/__init__.py
rare/components/tabs/library/integrations/egl_sync_group.py
rare/components/tabs/library/integrations/eos_group.py
rare/components/tabs/library/integrations/import_group.py
rare/components/tabs/library/integrations/ubisoft_group.py
rare/components/tabs/library/widgets/__init__.py
rare/components/tabs/library/widgets/game_widget.py
rare/components/tabs/library/widgets/icon_game_widget.py
rare/components/tabs/library/widgets/icon_widget.py
rare/components/tabs/library/widgets/library_widget.py
Rare-1.11.3.0.dist-info/LICENSE
Rare-1.11.3.0.dist-info/METADATA
Rare-1.11.3.0.dist-info/WHEEL
Rare-1.11.3.0.dist-info/entry_points.txt
Rare-1.11.3.0.dist-info/top_level.txt
Rare-1.11.3.0.dist-info/RECORD
