Metadata-Version: 2.2
Name: Rare
Version: 1.11.3.0
Summary: Open source alternative for Epic Games Launcher, using Legendary
Author-email: Dummerle <44114474+Dummerle@users.noreply.github.com>, loathingKernel <142770+loathingKernel@users.noreply.github.com>
Maintainer-email: loathingKernel <142770+loathingKernel@users.noreply.github.com>
License:                     GNU GENERAL PUBLIC LICENSE
Project-URL: Homepage, https://raredevs.github.io/Rare/
Project-URL: Repository, https://github.com/RareDevs/Rare
Project-URL: Issues, https://github.com/RareDevs/Rare/issues
Classifier: Programming Language :: Python :: 3.9
Classifier: Programming Language :: Python :: 3.10
Classifier: Programming Language :: Python :: 3.11
Classifier: Programming Language :: Python :: 3.12
Classifier: Programming Language :: Python :: 3.13
Classifier: License :: OSI Approved :: GNU General Public License v3 or later (GPLv3+)
Classifier: Operating System :: OS Independent
Requires-Python: >=3.9
License-File: LICENSE
Requires-Dist: requests<3.0
Requires-Dist: PySide6-Essentials>=6.8.1
Requires-Dist: QtAwesome
Requires-Dist: legendary-gl>=0.20.34
Requires-Dist: orjson
Requires-Dist: vdf
Requires-Dist: pywin32; platform_system == "Windows"
Provides-Extra: webview
Requires-Dist: pywebview[gtk]; platform_system == "Linux" and extra == "webview"
Requires-Dist: pywebview[gtk]; platform_system == "FreeBSD" and extra == "webview"
Requires-Dist: pythonnet; platform_system == "Windows" and extra == "webview"
Requires-Dist: pywebview; platform_system == "Windows" and extra == "webview"
Requires-Dist: pyobjc; platform_system == "Darwin" and extra == "webview"
Requires-Dist: pywebview; platform_system == "Darwin" and extra == "webview"
Provides-Extra: discordrpc
Requires-Dist: pypresence; extra == "discordrpc"
Provides-Extra: dev
Requires-Dist: pylint; extra == "dev"
Requires-Dist: mypy; extra == "dev"
Requires-Dist: black[d]; extra == "dev"
Requires-Dist: PySide6-stubs; extra == "dev"
Requires-Dist: qstylizer; extra == "dev"
Provides-Extra: packaging
Requires-Dist: cx-freeze; extra == "packaging"
Requires-Dist: nuitka; extra == "packaging"
Requires-Dist: pyinstaller; extra == "packaging"
